main.py
visacontrol-0.1.0.dist-info/METADATA
visacontrol-0.1.0.dist-info/WHEEL
visacontrol-0.1.0.dist-info/top_level.txt
visacontrol-0.1.0.dist-info/RECORD
