Metadata-Version: 2.4
Name: visacontrol
Version: 0.1.0
Summary: A MCP server to control instruments through visa
Requires-Python: >=3.10
Requires-Dist: mcp[cli]>=1.8.0
Requires-Dist: pyvisa>=1.14.1
Requires-Dist: pyvisa-py>=0.7.2
